{
    "fluentMethods": true,
    "relationships": [
        {
            "relationshipName": "profesor",
            "otherEntityName": "profesor",
            "relationshipType": "many-to-many",
            "otherEntityField": "id",
            "ownerSide": true,
            "otherEntityRelationshipName": "asignatura"
        }
    ],
    "fields": [
        {
            "fieldName": "nombre",
            "fieldType": "String",
            "fieldValidateRules": [
                "required"
            ]
        },
        {
            "fieldName": "plan",
            "fieldType": "String",
            "fieldValidateRules": [
                "required"
            ]
        },
        {
            "fieldName": "titulacion",
            "fieldType": "String",
            "fieldValidateRules": [
                "required"
            ]
        },
        {
            "fieldName": "creditos",
            "fieldType": "Integer",
            "fieldValidateRules": [
                "required"
            ]
        },
        {
            "fieldName": "num_grupos",
            "fieldType": "Integer"
        },
        {
            "fieldName": "creditos_teoricos",
            "fieldType": "Integer",
            "fieldValidateRules": [
                "required"
            ]
        },
        {
            "fieldName": "creditos_practicas",
            "fieldType": "Integer",
            "fieldValidateRules": [
                "required"
            ]
        },
        {
            "fieldName": "num_grupos_teoricos",
            "fieldType": "Integer"
        },
        {
            "fieldName": "num_grupos_practicas",
            "fieldType": "Integer"
        },
        {
            "fieldName": "usu_alta",
            "fieldType": "String",
            "fieldValidateRules": [
                "required"
            ]
        }
    ],
    "changelogDate": "20171008213459",
    "dto": "no",
    "service": "no",
    "entityTableName": "asignatura",
    "pagination": "pager"
}
